dysts/__init__.py
dysts/analysis.py
dysts/attractor.py
dysts/base.py
dysts/coupling.py
dysts/flows.py
dysts/generator.py
dysts/maps.py
dysts/metrics.py
dysts/sampling.py
dysts/systems.py
dysts/data/all_attractors.jpg
dysts/data/all_attractors.png
dysts/data/chaotic_attractors.json
dysts/data/discrete_maps.json
dysts/data/fig_github.png
dysts/data/logo.png
dysts/data/lyapunov_exponents_naive_mean.txt
dysts/data/lyapunov_exponents_naive_median.txt
dysts/data/lyapunov_exponents_naive_short.txt
dysts/data/lyapunov_exponents_qr.txt
dysts/utils/__init__.py
dysts/utils/data_utils.py
dysts/utils/integration_utils.py
dysts/utils/native_utils.py
dysts/utils/utils.py
dysts-0.96.dist-info/licenses/LICENSE.md
dysts-0.96.dist-info/METADATA
dysts-0.96.dist-info/WHEEL
dysts-0.96.dist-info/top_level.txt
dysts-0.96.dist-info/RECORD
