Metadata-Version: 2.4
Name: dysts
Version: 0.96
Summary: More than 100 strange attractors
Classifier: Programming Language :: Python :: 3
Classifier: License :: OSI Approved :: MIT License
Classifier: Operating System :: OS Independent
Requires-Python: >=3.10
License-File: LICENSE.md
Requires-Dist: numpy
Requires-Dist: matplotlib
Requires-Dist: scipy
Requires-Dist: scikit-learn
Requires-Dist: tqdm
Requires-Dist: gluonts[arrow]
Provides-Extra: benchmarks
Requires-Dist: darts; extra == "benchmarks"
Requires-Dist: torch; extra == "benchmarks"
Requires-Dist: pandas; extra == "benchmarks"
Provides-Extra: numba
Requires-Dist: numba; extra == "numba"
Provides-Extra: extra
Requires-Dist: sdeint; extra == "extra"
Requires-Dist: wandb; extra == "extra"
Requires-Dist: statsmodels; extra == "extra"
Dynamic: license-file
